{
  "main": {
    "id": "01f1b4b2ac089e58",
    "type": "split",
    "children": [
      {
        "id": "febc8ce228615392",
        "type": "tabs",
        "children": [
          {
            "id": "b00fd6bc18e9f778",
            "type": "leaf",
            "state": {
              "type": "empty",
              "state": {},
              "icon": "lucide-file",
              "title": "新标签页"
            }
          }
        ]
      },
      {
        "id": "8fc91a01727f271b",
        "type": "tabs",
        "children": [
          {
            "id": "2e11910d92220667",
            "type": "leaf",
            "state": {
              "type": "markdown",
              "state": {
                "file": "书籍/05-信息论.md",
                "mode": "source",
                "source": false
              },
              "icon": "lucide-file",
              "title": "05-信息论"
            }
          }
        ]
      }
    ],
    "direction": "vertical"
  },
  "left": {
    "id": "7895db49749702ee",
    "type": "split",
    "children": [
      {
        "id": "28f6790db0396f7f",
        "type": "tabs",
        "children": [
          {
            "id": "549e0cfdf283172a",
            "type": "leaf",
            "state": {
              "type": "file-explorer",
              "state": {
                "sortOrder": "alphabetical",
                "autoReveal": false
              },
              "icon": "lucide-folder-closed",
              "title": "文件列表"
            }
          },
          {
            "id": "389cf3c53c5f63c5",
            "type": "leaf",
            "state": {
              "type": "search",
              "state": {
                "query": "",
                "matchingCase": false,
                "explainSearch": false,
                "collapseAll": false,
                "extraContext": false,
                "sortOrder": "alphabetical"
              },
              "icon": "lucide-search",
              "title": "搜索"
            }
          },
          {
            "id": "241c0595ed3445a0",
            "type": "leaf",
            "state": {
              "type": "bookmarks",
              "state": {},
              "icon": "lucide-bookmark",
              "title": "书签"
            }
          }
        ]
      }
    ],
    "direction": "horizontal",
    "width": 300
  },
  "right": {
    "id": "34a04d55d3ee6190",
    "type": "split",
    "children": [
      {
        "id": "25d6dfd0eee377e1",
        "type": "tabs",
        "children": [
          {
            "id": "c87485fe5eac9197",
            "type": "leaf",
            "state": {
              "type": "backlink",
              "state": {
                "file": "欢迎.md",
                "collapseAll": false,
                "extraContext": false,
                "sortOrder": "alphabetical",
                "showSearch": false,
                "searchQuery": "",
                "backlinkCollapsed": false,
                "unlinkedCollapsed": true
              },
              "icon": "links-coming-in",
              "title": "欢迎 的反向链接列表"
            }
          },
          {
            "id": "5b8fcb5e91d98be4",
            "type": "leaf",
            "state": {
              "type": "outgoing-link",
              "state": {
                "file": "欢迎.md",
                "linksCollapsed": false,
                "unlinkedCollapsed": true
              },
              "icon": "links-going-out",
              "title": "欢迎 的出链列表"
            }
          },
          {
            "id": "d52e651d4795fba9",
            "type": "leaf",
            "state": {
              "type": "tag",
              "state": {
                "sortOrder": "frequency",
                "useHierarchy": true,
                "showSearch": false,
                "searchQuery": ""
              },
              "icon": "lucide-tags",
              "title": "标签"
            }
          },
          {
            "id": "67e4c8d9bf5dbc39",
            "type": "leaf",
            "state": {
              "type": "all-properties",
              "state": {
                "sortOrder": "frequency",
                "showSearch": false,
                "searchQuery": ""
              },
              "icon": "lucide-archive",
              "title": "添加笔记属性"
            }
          },
          {
            "id": "23e3d98fa4f3e734",
            "type": "leaf",
            "state": {
              "type": "outline",
              "state": {
                "file": "欢迎.md",
                "followCursor": false,
                "showSearch": false,
                "searchQuery": ""
              },
              "icon": "lucide-list",
              "title": "欢迎 的大纲"
            }
          }
        ]
      }
    ],
    "direction": "horizontal",
    "width": 300,
    "collapsed": true
  },
  "left-ribbon": {
    "hiddenItems": {
      "switcher:打开快速切换": false,
      "graph:查看关系图谱": false,
      "canvas:新建白板": false,
      "daily-notes:打开/创建今天的日记": false,
      "templates:插入模板": false,
      "command-palette:打开命令面板": false,
      "bases:新建数据库": false
    }
  },
  "active": "2e11910d92220667",
  "lastOpenFiles": [
    "书籍/01-优选学.md",
    "控制论书本总结.md",
    "概念/非线性系统.md",
    "核心理论与概念.md",
    "OCR全文/34-质量控制.md",
    "OCR全文/23-最优控制计算方法.md",
    "OCR全文/04-信号流图和系统.md",
    "知识图谱.md",
    "总体大纲.md",
    "欢迎.md",
    "OCR全文/17-最优停止理论.md",
    "书籍/17-最优停止理论.md",
    "deep-ocr-run.err.log",
    "deep-ocr-run.log",
    "manifest.json",
    "概念/控制图.md",
    "概念/质量控制.md",
    "概念/模糊测度.md",
    "概念/最优设计.md",
    "概念/最优停止.md",
    "概念/优选法.md",
    "概念/鲁棒性.md",
    "概念/灵敏度.md",
    "概念/参数辨识.md",
    "概念/自适应控制.md",
    "概念/随机控制.md",
    "概念/Kalman滤波.md",
    "概念/Riccati方程.md",
    "概念/LQR.md",
    "OCR页数据/34-质量控制.jsonl",
    "OCR页数据/32-系统灵敏度理论导论.jsonl",
    "OCR页数据/33-线性系统理论.jsonl",
    "OCR页数据/31-现代控制理论基础例题与习题.jsonl",
    "OCR页数据/30-现代控制理论基础.jsonl",
    "OCR页数据/28-状态变量分析导论.jsonl",
    "OCR页数据/29-状态空间分析导论上-下.jsonl"
  ]
}